{
    "MenuBar": {
        "type" : "",
       
        "menus" : {
            "home" : {
                "type" : "Icon",
                "resource" : "",
                "triggers" : "onHomeClick"
            },

            "view" : {
                "type" : "Text",
                "triggers" : "onViewClick",
                "items" : {
                    "Sort Algorithms" : {
                        "type" : "CheckBox",
                        "triggers" : "onSortClick"
                    },
                    "Search Algorithms" : {
                        "type" : "CheckBox",
                        "triggers" : "onSearchClick"
                    },
                    "Graph Algorithms" : {
                        "type" : "CheckBox",
                        "triggers" : "onGraphClick"
                    },
                    "Data Structures" : {
                        "type" : "CheckBox",
                        "triggers" : "onDSClick"
                    },
                    "ML Algorithms" : {
                        "type" : "CheckBox",
                        "triggers" : "onMLClick"
                    }
                }
            },

            "API" : {
                "type" : "Text",
                "triggers" : "onAPIClick",
                "items" : {
                    "Reference" : {
                        "type" : "Text",
                        "triggers" : "onReferenceClick"
                    },
                    "Upload an algorithm" : {
                        "type" : "Text",
                        "triggers" : "onUploadClick"
                    }
                }
            },

            "Help" : {
                "type" : "Text",
                "triggers" : "onHelpClick",
                "items" : {
                    "Visit Online Guide" : {
                        "type" : "Text",
                        "triggers" : "onVisitClick"
                    },
                    "About" : {
                        "type" : "Text",
                        "triggers" : "onAboutClick"
                    }
                }
            }
        }   
    }
}